django_relinking
